torch_smoke/__about__.py
torch_smoke/__init__.py
torch_smoke-0.1.0.dist-info/METADATA
torch_smoke-0.1.0.dist-info/WHEEL
torch_smoke-0.1.0.dist-info/licenses/LICENSE
torch_smoke-0.1.0.dist-info/RECORD
